bfportal_grpc/__init__.py
bfportal_grpc/access_token.py
bfportal_grpc/proto/__init__.py
bfportal_grpc/proto/authentication_pb2.py
bfportal_grpc/proto/authentication_pb2_grpc.py
bfportal_grpc/proto/communitygames_pb2.py
bfportal_grpc/proto/communitygames_pb2_grpc.py
bfportal_grpc/proto/localization_pb2.py
bfportal_grpc/proto/localization_pb2_grpc.py
bfportal_grpc/proto/reporting_pb2.py
bfportal_grpc/proto/reporting_pb2_grpc.py
bfportal_grpc-0.1.4.dist-info/METADATA
bfportal_grpc-0.1.4.dist-info/WHEEL
bfportal_grpc-0.1.4.dist-info/RECORD
