Metadata-Version: 2.1
Name: bfportal-grpc
Version: 0.1.4
Summary:  bf2042 portal web grpc as python package 
Home-page: https://github.com/community-network/bfportal-grpc
Keywords: bfportal,grpc,Battlefield portal
Author: iiTzArcur
Author-email: arcur@gametools.network
Requires-Python: >=3.10,<4.0
Classifier: Programming Language :: Python
Classifier: Programming Language :: Python :: 3
Classifier: Programming Language :: Python :: 3.10
Classifier: Programming Language :: Python :: 3.11
Requires-Dist: aiohttp (>=3.8.1,<4.0.0)
Requires-Dist: grpcio (==1.48.1)
Requires-Dist: protobuf (==4.21.6)
Project-URL: Bug Tracker, https://github.com/community-network/bfportal-grpc/issues
Project-URL: Repository, https://github.com/community-network/bfportal-grpc
